src/__init__.py
src/sem_ver.py
py_semver-0.0.3.dist-info/METADATA
py_semver-0.0.3.dist-info/WHEEL
py_semver-0.0.3.dist-info/entry_points.txt
py_semver-0.0.3.dist-info/top_level.txt
py_semver-0.0.3.dist-info/RECORD
