Metadata-Version: 2.1
Name: py-semver
Version: 0.0.3
Summary: A basic semver generator using conventional commit messages.
Home-page: https://github.com/abnvanand/py-semver
Author: Abhinav Anand
Author-email: abnvanand@gmail.com
License: MIT License
Platform: UNKNOWN
Classifier: Programming Language :: Python :: 3
Classifier: License :: OSI Approved :: MIT License
Classifier: Operating System :: POSIX
Classifier: Environment :: Console
